BLE_GATT/__init__.py
BLE_GATT/central.py
BLE_GATT-0.5.0.dist-info/LICENSE
BLE_GATT-0.5.0.dist-info/METADATA
BLE_GATT-0.5.0.dist-info/WHEEL
BLE_GATT-0.5.0.dist-info/top_level.txt
BLE_GATT-0.5.0.dist-info/RECORD
