Metadata-Version: 2.1
Name: BLE-GATT
Version: 0.5.0
Summary: Python library for Bluetooth Low Energy (BLE) Central on Linux
Home-page: https://github.com/ukBaz/BLE_GATT
Author: Barry Byford
Author-email: barry_byford@yahoo.co.uk
Maintainer: Barry Byford
Maintainer-email: barry_byford@yahoo.co.uk
License: MIT
Keywords: Bluetooth BLE development GATT Central
Platform: UNKNOWN
Classifier: Development Status :: 4 - Beta
Classifier: Intended Audience :: Developers
Classifier: Intended Audience :: Education
Classifier: Topic :: System :: Hardware
Classifier: Topic :: Software Development :: Embedded Systems
Classifier: Topic :: Home Automation
Classifier: Topic :: Education
Classifier: License :: OSI Approved :: MIT License
Classifier: Programming Language :: Python :: 3 :: Only
Requires-Dist: pydbus
Requires-Dist: vext.gi
Provides-Extra: dev
Requires-Dist: bumpversion ; extra == 'dev'
Requires-Dist: twine ; extra == 'dev'
Requires-Dist: sphinx ; extra == 'dev'
Requires-Dist: sphinx-rtd-theme ; extra == 'dev'
Requires-Dist: coverage ; extra == 'dev'
Requires-Dist: pycodestyle ; extra == 'dev'
Requires-Dist: python-dbusmock ; extra == 'dev'
Provides-Extra: docs
Requires-Dist: sphinx ; extra == 'docs'
Requires-Dist: sphinx-rtd-theme ; extra == 'docs'
Provides-Extra: rel
Requires-Dist: bumpversion ; extra == 'rel'
Requires-Dist: twine ; extra == 'rel'
Provides-Extra: test
Requires-Dist: coverage ; extra == 'test'
Requires-Dist: pycodestyle ; extra == 'test'
Requires-Dist: python-dbusmock ; extra == 'test'
